gitkit/GitRepository.py
gitkit/GitRepositoryFactory.py
gitkit/GitRepositoryService.py
gitkit/GitRepositoryState.py
gitkit/GithubRepositoryService.py
gitkit/GithubRepositoryType.py
gitkit/LogProvider.py
gitkit/Singleton.py
gitkit/__init__.py
gitkit/root.py
gitkit/Commands/CloneCommand.py
gitkit/Commands/CommandExecuter.py
gitkit/Commands/CommitCommand.py
gitkit/Commands/FindCommand.py
gitkit/Commands/PullCommand.py
gitkit/Commands/PushCommand.py
gitkit/Commands/__init__.py
gitkit/Models/CommandContext.py
gitkit/Models/Commands.py
gitkit/Models/Filters.py
gitkit/Models/__init__.py
gitkit-0.2.0.dist-info/LICENSE
gitkit-0.2.0.dist-info/METADATA
gitkit-0.2.0.dist-info/WHEEL
gitkit-0.2.0.dist-info/entry_points.txt
gitkit-0.2.0.dist-info/top_level.txt
gitkit-0.2.0.dist-info/RECORD
