Metadata-Version: 2.1
Name: gitkit
Version: 0.2.0
Summary: Keep your git repositories up to date
Home-page: https://github.com/dotupNET
Author: Peter Ullrich
Author-email: dotup.software@gmail.com
License: GNU General Public License v3.0
Keywords: dotup git github sync
Classifier: Development Status :: 2 - Pre-Alpha
Classifier: Environment :: Console
Classifier: Intended Audience :: Developers
Classifier: Intended Audience :: End Users/Desktop
Classifier: License :: OSI Approved :: GNU General Public License v3 or later (GPLv3+)
Classifier: Operating System :: OS Independent
Classifier: Programming Language :: Python :: 3.4
Classifier: Programming Language :: Python :: 3.5
Classifier: Programming Language :: Python :: 3.6
Classifier: Programming Language :: Python :: 3.7
Classifier: Topic :: Utilities
Requires-Python: >=3
License-File: LICENSE
Requires-Dist: Click
